BSD.LICENSE
CHANGES.txt
MANIFEST.in
README.rst
checkit.py
setup.py
checkit.egg-info/PKG-INFO
checkit.egg-info/SOURCES.txt
checkit.egg-info/dependency_links.txt
checkit.egg-info/entry_points.txt
checkit.egg-info/not-zip-safe
checkit.egg-info/requires.txt
checkit.egg-info/top_level.txt