Metadata-Version: 1.0
Name: checkit
Version: 0.2.3b
Summary: Validate your Python software against specifications created with BDD style grammar.
Home-page: https://bitbucket.org/rudylattae/checkit
Author: Rudy Lattae
Author-email: rudylattae@gmail.com
License: Simplified BSD
Keywords: Specification,BDD,TDD,check,validate,example,nose,nosetest
Platform: UNKNOWN
Classifier: Development Status :: 4 - Beta
Classifier: Environment :: Console
Classifier: Intended Audience :: Developers
Classifier: License :: OSI Approved :: BSD License
Classifier: Operating System :: Microsoft :: Windows
Classifier: Programming Language :: Python
Classifier: Programming Language :: Python :: 2.7
